Way2DSSAT/WTH.py
Way2DSSAT/__init__.py
Way2DSSAT/gssurgo2soil.py
Way2DSSAT/xfiles.py
Way2DSSAT-0.0.11.dist-info/METADATA
Way2DSSAT-0.0.11.dist-info/WHEEL
Way2DSSAT-0.0.11.dist-info/top_level.txt
Way2DSSAT-0.0.11.dist-info/RECORD
