Metadata-Version: 2.1
Name: Way2DSSAT
Version: 0.0.11
Summary: Package to handle input DSSAT files
Author: Manavjot Singh
Author-email: Manavjot <manavjotsingh97@gmail.com>
Project-URL: Homepage, https://github.com/ManavjotSingh97/Way2DSSAT
Project-URL: Issues, https://github.com/ManavjotSingh97/Way2DSSAT/issues
Keywords: python,DSSAT,Input,gSSURGO
Classifier: Programming Language :: Python :: 3
Classifier: License :: OSI Approved :: MIT License
Classifier: Operating System :: OS Independent
Requires-Python: >=3.8
Requires-Dist: pandas
